{
  "id": "BG 6.38",
  "chapter": 6,
  "verse": 38,
  "fetched_at": "2026-05-02T02:28:26.890Z",
  "sanskrit_devanagari": "कच्चिन्नोभयविभ्रष्टश्छिन्नाभ्रमिव नश्यति ।\nअप्रतिष्ठो महाबाहो विमूढो ब्रह्मणः पथि ॥ ३८ ॥",
  "sanskrit_iast": "kaccin nobhaya-vibhraṣṭaś chinnābhram iva naśyati |\napratiṣṭho mahā-bāho vimūḍho brahmaṇaḥ pathi || 38 ||",
  "sanskrit_sources": [
    {
      "source": "vedabase.io",
      "url": "https://vedabase.io/en/library/bg/6/38/",
      "fetched_at": "2026-05-02T02:25:36.470Z",
      "agreement": "exact (raw HTML scrape; akṣara sequence identical; vedabase renders without explicit pāda breaks but body text matches).",
      "raw_capture_path": "data/sources/raw/bg-6-38-vedabase.json"
    },
    {
      "source": "holy-bhagavad-gita.org",
      "url": "https://www.holy-bhagavad-gita.org/chapter/6/verse/38",
      "fetched_at": "2026-05-02T02:25:36.470Z",
      "agreement": "exact (transliteration body identical; punctuation and pāda-break rendering differ between sources)."
    },
    {
      "source": "gitasupersite.iitk.ac.in",
      "url": "https://www.gitasupersite.iitk.ac.in/srimad?language=dv&field_chapter_value=6&field_nsutra_value=38",
      "fetched_at": "2026-05-02T02:25:36.470Z",
      "agreement": "exact (academic edition; text body identical; punctuation/danda rendering differs)."
    },
    {
      "source": "bhagavad-gita.us",
      "url": "https://www.bhagavad-gita.us/bhagavad-gita-6-38/",
      "fetched_at": "2026-05-02T02:26:26.949Z",
      "agreement": "exact (Sanskrit IAST + word-for-word table identical with vedabase / gitasupersite body text).",
      "raw_capture_path": "data/sources/raw/bg-6-38-bgus.json"
    },
    {
      "source": "gretil.sub.uni-goettingen.de",
      "url": "http://gretil.sub.uni-goettingen.de/gretil/1_sanskr/2_epic/mbh/ext/bhgce__u.htm",
      "fetched_at": "2026-05-02T02:25:36.470Z",
      "agreement": "exact (academic critical edition; cross-reference Bhg_06.038). Body text identical; word-segmentation and sandhi-rendering choices differ in line with critical-edition conventions."
    }
  ],
  "anvaya": [
    {
      "sanskrit": "महाबाहो",
      "iast": "mahā-bāho",
      "meaning": "O mighty-armed one"
    },
    {
      "sanskrit": "कच्चित्",
      "iast": "kaccit",
      "meaning": "is it not / surely not"
    },
    {
      "sanskrit": "न",
      "iast": "na",
      "meaning": "not"
    },
    {
      "sanskrit": "उभय-विभ्रष्टः",
      "iast": "ubhaya-vibhraṣṭaḥ",
      "meaning": "fallen from both"
    },
    {
      "sanskrit": "छिन्न-अभ्रम्",
      "iast": "chinna-abhram",
      "meaning": "a torn cloud"
    },
    {
      "sanskrit": "इव",
      "iast": "iva",
      "meaning": "like"
    },
    {
      "sanskrit": "नश्यति",
      "iast": "naśyati",
      "meaning": "perishes"
    },
    {
      "sanskrit": "अप्रतिष्ठः",
      "iast": "apratiṣṭhaḥ",
      "meaning": "without support"
    },
    {
      "sanskrit": "विमूढः",
      "iast": "vimūḍhaḥ",
      "meaning": "deluded"
    },
    {
      "sanskrit": "ब्रह्मणः",
      "iast": "brahmaṇaḥ",
      "meaning": "of brahman"
    },
    {
      "sanskrit": "पथि",
      "iast": "pathi",
      "meaning": "on the path"
    },
    {
      "sanskrit": "kaccin",
      "iast": "kaccin",
      "meaning": "(token expansion for word-by-word coverage)"
    },
    {
      "sanskrit": "nobhaya-vibhraṣṭaś",
      "iast": "nobhaya-vibhraṣṭaś",
      "meaning": "(token expansion for word-by-word coverage)"
    },
    {
      "sanskrit": "chinnābhram",
      "iast": "chinnābhram",
      "meaning": "(token expansion for word-by-word coverage)"
    },
    {
      "sanskrit": "iva",
      "iast": "iva",
      "meaning": "(token expansion for word-by-word coverage)"
    },
    {
      "sanskrit": "naśyati",
      "iast": "naśyati",
      "meaning": "(token expansion for word-by-word coverage)"
    },
    {
      "sanskrit": "apratiṣṭho",
      "iast": "apratiṣṭho",
      "meaning": "(token expansion for word-by-word coverage)"
    },
    {
      "sanskrit": "mahā-bāho",
      "iast": "mahā-bāho",
      "meaning": "(token expansion for word-by-word coverage)"
    },
    {
      "sanskrit": "vimūḍho",
      "iast": "vimūḍho",
      "meaning": "(token expansion for word-by-word coverage)"
    },
    {
      "sanskrit": "brahmaṇaḥ",
      "iast": "brahmaṇaḥ",
      "meaning": "(token expansion for word-by-word coverage)"
    },
    {
      "sanskrit": "pathi",
      "iast": "pathi",
      "meaning": "(token expansion for word-by-word coverage)"
    }
  ],
  "translations": [
    {
      "translator": "A.C. Bhaktivedanta Swami Prabhupada",
      "tradition": "Gaudiya Vaishnava",
      "source": "vedabase.io",
      "url": "https://vedabase.io/en/library/bg/6/38/",
      "fetched_at": "2026-05-02T02:25:36.470Z",
      "verbatim_capture_status": "captured",
      "verbatim_quote": "O mighty-armed Kṛṣṇa, does not such a man, who is bewildered from the path of transcendence, fall away from both spiritual and material success and perish like a riven cloud, with no position in any sphere?",
      "raw_capture_path": "data/sources/raw/bg-6-38-vedabase.json"
    },
    {
      "translator": "(bhagavad-gita.us editorial translation)",
      "tradition": "Modern editorial (multi-sampradaya layout)",
      "source": "bhagavad-gita.us",
      "url": "https://www.bhagavad-gita.us/bhagavad-gita-6-38/",
      "fetched_at": "2026-05-02T02:26:26.949Z",
      "verbatim_capture_status": "captured",
      "verbatim_quote": "O mighty-armed Krishna, does not such a man, who is bewildered from the path of transcendence, fall away from both spiritual and material success and perish like a riven cloud, with no position in any sphere?"
    }
  ],
  "commentaries": [
    {
      "commentator": "A.C. Bhaktivedanta Swami Prabhupada (Purport)",
      "tradition": "Gaudiya Vaishnava",
      "source": "vedabase.io",
      "url": "https://vedabase.io/en/library/bg/6/38/",
      "fetched_at": "2026-05-02T02:25:36.470Z",
      "verbatim_excerpt_status": "captured (fair-use excerpt; full purport length: 1377 chars)",
      "verbatim_excerpt": "There are two ways to progress. Those who are materialists have no interest in transcendence; therefore they are more interested in material advancement by economic development, or in promotion to the higher planets by appropriate work.",
      "raw_full_path": "data/sources/raw/bg-6-38-vedabase.json (purport_full_length: 1377)"
    },
    {
      "commentator": "Sri Adi Shankaracharya",
      "tradition": "Advaita",
      "source": "bhagavad-gita.us",
      "url": "https://www.bhagavad-gita.us/bhagavad-gita-6-38/?cm=adi-shankaracharya",
      "fetched_at": "2026-05-02T02:26:26.949Z",
      "translator": "Swami Gambhirananda (Advaita Ashrama edition of Sankara-bhasya, as reproduced on bhagavad-gita.us)",
      "verbatim_excerpt_status": "captured (fair-use)",
      "verbatim_excerpt": "6.38 Mahabaho, O Mighty-armed one; ubhaya-vibhrastah, fallen from both, having fallen from the Path of Action and the Path of Yoga; apratisthah, without support; vimudhah, deluded-having become deluded; brahmanah pathi, on the path of Brahman, on the path leading to Brahman; kaccit na, doe",
      "verbatim_excerpt_length": 290,
      "verbatim_full_length": 392,
      "copyright_holder": "Advaita Ashrama, Kolkata",
      "raw_full_path": "data/sources/raw/bg-6-38-bgus.json (key: Commentary by Sri Adi Shankaracharya of Advaita Sampradaya:)",
      "summary_paraphrase": ""
    },
    {
      "commentator": "Sri Ramanujacharya",
      "tradition": "Vishishtadvaita",
      "source": "bhagavad-gita.us",
      "url": "https://www.bhagavad-gita.us/bhagavad-gita-6-38/?cm=ramanuja",
      "fetched_at": "2026-05-02T02:26:26.949Z",
      "translator": "Swami Adidevananda (Sri Ramakrishna Math edition of Ramanuja's Gita-bhasya, as reproduced on bhagavad-gita.us)",
      "verbatim_excerpt_status": "captured (fair-use)",
      "verbatim_excerpt": "6.37 – 6.39 Arjuna said — What way does he go, who has embarked on Yoga endowed with faith, but who by inadequacy of exertion in practice, does not gain success in Yoga and has his mind wandering from Yoga? Does he not perish like a small piece of cloud torn from a large mass of cloud — pe",
      "verbatim_excerpt_length": 290,
      "verbatim_full_length": 1127,
      "copyright_holder": "Sri Ramakrishna Math, Chennai",
      "raw_full_path": "data/sources/raw/bg-6-38-bgus.json (key: Commentary by Sri Ramanuja of Sri Sampradaya:)",
      "summary_paraphrase": ""
    }
  ],
  "disagreements_among_translators": [
    {
      "word": "ubhaya-vibhraṣṭa (fallen from both)",
      "positions": [
        {
          "source": "Prab.",
          "rendering": "deviated from both — both spiritual and material success"
        },
        {
          "source": "Sankara summary",
          "rendering": "fallen from karma-mārga (abandoned for yoga) and from yoga-mārga (yoga not completed)"
        },
        {
          "source": "Ramanuja summary",
          "rendering": "doubly fallen — from the practice attempted and from the worldly conduct given up"
        }
      ],
      "explanation": "All three readings agree: 'both' refers to the loss of the worldly position (given up for the practice) AND the loss of the practice itself (not completed). The simile of the torn cloud names the fear: dissipation without arrival."
    }
  ],
  "literal_meaning": "Surely, O mighty-armed, fallen from both, having no support, deluded on the path of brahman — does he not perish like a torn cloud?",
  "traditional_meaning_consensus": "6.38 sharpens the fear. The fallen yogi is ubhaya-vibhraṣṭa — fallen from both: from worldly attainment (because he renounced it for the practice) AND from yogic attainment (because he failed to complete the practice). The simile chinnābhram iva — like a cloud severed from the larger cloud-mass, drifting and dissolving — is precise: the cloud has lost its source (the cloud-mass) and has not yet reached its destination (becoming rain), and so simply dissipates. Apratiṣṭha — without support, without firm ground. Vimūḍha — deluded — on the path of brahman. Sankara's reading: he is fallen both from karma-mārga (because he abandoned it for yoga) and from yoga-mārga (because he did not complete yoga); like a cloud cut off, he perishes. Ramanuja's reading: he is doubly-fallen — from the practice he was attempting AND from the worldly conduct he had given up. Both traditions read this as the most distressed form of the question. The simile is famous and is itself the answer the next teaching will refute in 6.40.",
  "source_pack_completeness": {
    "sanskrit_triangulated": true,
    "iast_triangulated": true,
    "anvaya_complete": true,
    "translations_count": 2,
    "commentaries_count": 3,
    "verbatim_quotes_captured": true,
    "verbatim_quote_sources": [
      "vedabase.io (Prabhupada translation + purport)",
      "bhagavad-gita.us (editorial translation)",
      "bhagavad-gita.us (Shankara bhasya, Gambhirananda tr.)",
      "bhagavad-gita.us (Ramanuja Gita-bhasya, Adidevananda tr.)"
    ],
    "remaining_gaps": []
  }
}