{
  "source": "bhagavad-gita.us",
  "url": "https://www.bhagavad-gita.us/bhagavad-gita-2-25/",
  "fetched_at": "2026-04-29T18:20:21.922Z",
  "commentaries": {
    "Translation of Bhagavad Gita 2.25": "It is said that the soul is invisible, inconceivable and immutable. Knowing this, you should not grieve for the body.",
    "Commentary by Sri Vishvanatha Chakravarthi Thakur of Gaudiya Sampradaya:": "(combined commentary for verses 24 and 25)",
    "Commentary by Sri Madhvacharya of Brahma Sampradaya:": "he Supreme Lord is verily the manifestation of the inconceivable Himself.",
    "Sanskrit to English Word for Word Meanings:": "avyaktaḥ — invisible; ayam — this soul; acintyaḥ — inconceivable; ayam — this soul; avikāryaḥ — unchangeable; ayam — this soul; ucyate — is said; tasmāt — therefore; evam — like this; viditvā — knowing it well; enam — this soul; na — do not; anuśocitum — to lament; arhasi — you deserve."
  }
}
